{
    "sepolia":{
        "0x790ae803b6c0467C6A4cbDc6d6d712DE34CfdB76":{
            "name": "FeeTakingHookExample",
            "summary": "safe",
            "review": "./FeeTakingHook.md",
            "warnings": []
        },
        "0x2Aa9D4066DAe16ef001765efF2cA8F41Bde0b019":{
            "name": "ExitFeeHookExample",
            "summary": "safe",
            "review": "./ExitFeeHook.md",
            "warnings": []
        },
        "0xD9e535a65eb38F962B84f7BBD2bf60293bA54058":{
            "name": "DirectionalFeeHookExample",
            "summary": "safe",
            "review": "./DirectionalFeeHook.md",
            "warnings": []
        },
        "0x0E85194F9eD75F0EFf2b89B73b6AD3053be03853":{
            "name": "LotteryHookExample",
            "summary": "safe",
            "review": "./LotteryHook.md",
            "warnings": []
        },
        "0x1adc55adb4caae71abb4c33f606493f4114d2091":{
            "name": "StableSurgeHook",
            "summary": "safe",
            "review": "./StableSurge.md",
            "warnings": []
        }
    }
}